pydotenvx/__init__.py
pydotenvx/__main__.py
pydotenvx/commands.py
pydotenvx/parsing.py
pydotenvx-0.1.1.dist-info/LICENSE
pydotenvx-0.1.1.dist-info/METADATA
pydotenvx-0.1.1.dist-info/WHEEL
pydotenvx-0.1.1.dist-info/entry_points.txt
pydotenvx-0.1.1.dist-info/RECORD
